cli/__init__.py
cli/cli.py
cli/cli_export_subparser.py
cli/cli_import_subparser.py
cli/cli_pg_server_config_subparser.py
cli/cli_pgconfig_subparser.py
cli/cli_settings_subparser.py
cli/cli_toplevel_parser.py
pgmonkey/__init__.py
pgmonkey/common/__init__.py
pgmonkey/common/config/__init__.py
pgmonkey/common/templates/postgres.yaml
pgmonkey/common/utils/__init__.py
pgmonkey/common/utils/pathutils.py
pgmonkey/connections/__init__.py
pgmonkey/connections/base.py
pgmonkey/connections/postgres/__init__.py
pgmonkey/connections/postgres/async_connection.py
pgmonkey/connections/postgres/async_pool_connection.py
pgmonkey/connections/postgres/base_connection.py
pgmonkey/connections/postgres/normal_connection.py
pgmonkey/connections/postgres/pool_connection.py
pgmonkey/connections/postgres/postgres_connection_factory.py
pgmonkey/managers/__init__.py
pgmonkey/managers/pg_server_config_manager.py
pgmonkey/managers/pgcodegen_manager.py
pgmonkey/managers/pgconfig_manager.py
pgmonkey/managers/pgconnection_manager.py
pgmonkey/managers/pgexport_manager.py
pgmonkey/managers/pgimport_manager.py
pgmonkey/managers/settings_manager.py
pgmonkey/managers/toplevel_manager.py
pgmonkey/serversettings/postgres_server_config_generator.py
pgmonkey/settings/app_settings.yaml
pgmonkey/tools/__init__.py
pgmonkey/tools/connection_code_generator.py
pgmonkey/tools/csv_data_exporter.py
pgmonkey/tools/csv_data_importer.py
pgmonkey/tools/database_connection_tester.py
tests/integration/test_pgconnection_manager_integration.py
pgmonkey-1.1.6.dist-info/LICENSE
pgmonkey-1.1.6.dist-info/METADATA
pgmonkey-1.1.6.dist-info/NOTICE
pgmonkey-1.1.6.dist-info/WHEEL
pgmonkey-1.1.6.dist-info/entry_points.txt
pgmonkey-1.1.6.dist-info/top_level.txt
pgmonkey-1.1.6.dist-info/RECORD
