Metadata-Version: 2.1
Name: pgmonkey
Version: 1.1.6
Summary: A tool to assist with postgresql database connections
Author-email: Good Boy <pythonic@rexbytes.com>
License: MIT License
Project-URL: Homepage, https://pgmonkey.net
Project-URL: Repository, https://github.com/RexBytes/pgmonkey
Project-URL: Bug Tracker, https://github.com/RexBytes/pgmonkey
Classifier: Programming Language :: Python :: 3.9
Classifier: Programming Language :: Python :: 3.10
Classifier: Programming Language :: Python :: 3.11
Classifier: Programming Language :: Python :: 3.12
Classifier: License :: OSI Approved :: MIT License
Classifier: Operating System :: OS Independent
Classifier: Topic :: Database
Classifier: Topic :: Software Development :: Libraries :: Python Modules
Requires-Python: <3.13,>=3.9
License-File: LICENSE
License-File: NOTICE
Requires-Dist: psycopg[binary]<4.0.0,>=3.1.20
Requires-Dist: psycopg_pool<4.0.0,>=3.1.9
Requires-Dist: PyYAML<7.0.0,>=6.0.2
Requires-Dist: chardet<6.0.0,>=5.2.0
Requires-Dist: aiofiles<23.0.0,>=22.1.0
Requires-Dist: tqdm<5.0.0,>=4.64.0
